pysurfex/__init__.py
pysurfex/binary_input.py
pysurfex/bufr.py
pysurfex/cache.py
pysurfex/cfg/config.yml
pysurfex/cfg/config_deode_dt.yml
pysurfex/cfg/default_thredds.cfg
pysurfex/cfg/first_guess.yml
pysurfex/cfg/qc_codes.json
pysurfex/cfg/user.yml
pysurfex/cli.py
pysurfex/cmd_parsing.py
pysurfex/datetime_utils.py
pysurfex/fa.py
pysurfex/file.py
pysurfex/forcing.py
pysurfex/geo.py
pysurfex/grib.py
pysurfex/input_methods.py
pysurfex/interpolation.py
pysurfex/namelist.py
pysurfex/netcdf.py
pysurfex/obs.py
pysurfex/observation.py
pysurfex/obsmon.py
pysurfex/obsoul.py
pysurfex/platform_deps.py
pysurfex/plot.py
pysurfex/pseudoobs.py
pysurfex/read.py
pysurfex/run.py
pysurfex/settings/assimilation.json
pysurfex/settings/filetype.json
pysurfex/settings/forecast.json
pysurfex/settings/pgd.json
pysurfex/settings/prep.json
pysurfex/timeseries.py
pysurfex/titan.py
pysurfex/util.py
pysurfex/variable.py
pysurfex/verification.py
pysurfex-0.1.2.dist-info/METADATA
pysurfex-0.1.2.dist-info/WHEEL
pysurfex-0.1.2.dist-info/entry_points.txt
pysurfex-0.1.2.dist-info/RECORD
