Metadata-Version: 2.3
Name: pysurfex
Version: 0.1.2
Summary: Python API to SURFEX
License: MIT
Author: Trygve Aspelien
Requires-Python: >=3.10,<4.0
Classifier: License :: OSI Approved :: MIT License
Classifier: Programming Language :: Python :: 3
Classifier: Programming Language :: Python :: 3.10
Classifier: Programming Language :: Python :: 3.11
Classifier: Programming Language :: Python :: 3.12
Classifier: Programming Language :: Python :: 3.13
Provides-Extra: faformat
Provides-Extra: linting
Provides-Extra: netcdf
Provides-Extra: plot
Provides-Extra: points
Provides-Extra: test
Provides-Extra: verification
Requires-Dist: black[jupyter] (>=23.10.0) ; extra == "linting"
Requires-Dist: cartopy ; extra == "faformat"
Requires-Dist: cfunits (>=3.3.5) ; extra == "netcdf"
Requires-Dist: eccodes (>1.5.1) ; extra == "points"
Requires-Dist: epygram (>=2.0.0) ; extra == "faformat"
Requires-Dist: f90nml (>=1.4.3)
Requires-Dist: falfilfa4py (>=1.0.0) ; extra == "faformat"
Requires-Dist: findlibs (>=0.0.5,<=1.0.0) ; (python_version < "3.10") and (extra == "points")
Requires-Dist: gridpp (>=0.7.1) ; extra == "points"
Requires-Dist: isort (>=5.12.0) ; extra == "linting"
Requires-Dist: matplotlib (>=3.7.1) ; extra == "plot"
Requires-Dist: netcdf4 (>=1.5.7) ; extra == "netcdf"
Requires-Dist: numpy (>=1.20.1)
Requires-Dist: pandas (>=2.0.0) ; extra == "verification"
Requires-Dist: poethepoet[poetry-plugin] (>=0.24.4) ; extra == "linting"
Requires-Dist: pydoclint (>00.3.8) ; extra == "linting"
Requires-Dist: pyproj (>=3.3.0)
Requires-Dist: pytest (>=7.2.2) ; extra == "test"
Requires-Dist: pytest-cov (>=4.0.0) ; extra == "test"
Requires-Dist: pytest-mock (>=3.7.0) ; extra == "test"
Requires-Dist: pytest-profiling (>=1.7.0) ; extra == "test"
Requires-Dist: pytest-timeout (>=2.1.0) ; extra == "test"
Requires-Dist: pytest-xdist (>=3.2.0) ; extra == "test"
Requires-Dist: pyyaml (>=6.0) ; extra == "points"
Requires-Dist: requests (>=2.32.3) ; extra == "points"
Requires-Dist: ruff (>=0.11.0) ; extra == "linting"
Requires-Dist: sphinx (>=7.0.0) ; extra == "test"
Requires-Dist: titanlib (>=0.3.4.dev3) ; extra == "points"
Requires-Dist: verif (>=1.2.3) ; extra == "verification"
Requires-Dist: xarray (>=2025.3.1) ; extra == "verification"
